rgeocoder-0.1.6.dist-info/METADATA
rgeocoder-0.1.6.dist-info/WHEEL
rgeocoder-0.1.6.dist-info/license_files/LICENSE
rgeocoder/__init__.py
rgeocoder/cities.csv
rgeocoder/exceptions.py
rgeocoder/_rgeocoder.cpython-311-darwin.so
rgeocoder-0.1.6.dist-info/RECORD
