Metadata-Version: 2.1
Name: rgeocoder
Version: 0.1.6
Classifier: Development Status :: 3 - Alpha
Classifier: Intended Audience :: Developers
Classifier: License :: OSI Approved :: MIT License
Classifier: Programming Language :: Rust
Classifier: Programming Language :: Python :: Implementation :: CPython
Classifier: Programming Language :: Python :: 3
Classifier: Programming Language :: Python :: 3.7
Classifier: Programming Language :: Python :: 3.8
Classifier: Programming Language :: Python :: 3.9
Classifier: Programming Language :: Python :: 3.10
Classifier: Programming Language :: Python :: 3.11
License-File: LICENSE
Summary: A lightweight offline reverse geocoder implemented in Rust.
Keywords: reverse-geocoder,reverse-geocoding,geocoder,maturin,pyo3
Author: Phil V. <philippe@arcadian.be>
Author-email: Phil V. <philippe@arcadian.be>
License: MIT
Requires-Python: >=3.7
Project-URL: Documentation, https://phil-v.github.io/rgeocoder/
Project-URL: Repository, https://github.com/Phil-V/rgeocoder
Project-URL: History, https://github.com/Phil-V/rgeocoder/blob/master/HISTORY.rst
